README.rst
setup.py
utf9/__init__.py
utf9.egg-info/PKG-INFO
utf9.egg-info/SOURCES.txt
utf9.egg-info/dependency_links.txt
utf9.egg-info/requires.txt
utf9.egg-info/top_level.txt