Metadata-Version: 1.0
Name: utf9
Version: 0.3.1
Summary: Encode and decode text using UTF-9.
Home-page: http://github.com/enricobacis/utf9
Author: Enrico Bacis
Author-email: enrico.bacis@gmail.com
License: MIT
Keywords: utf9 encode decode rfc4042
Platform: UNKNOWN
